pyls/__init__.py
pyls/__main__.py
pyls/_utils.py
pyls/_version.py
pyls/hookspecs.py
pyls/lsp.py
pyls/python_ls.py
pyls/uris.py
pyls/workspace.py
pyls/config/__init__.py
pyls/config/config.py
pyls/config/flake8_conf.py
pyls/config/pycodestyle_conf.py
pyls/config/source.py
pyls/plugins/__init__.py
pyls/plugins/autopep8_format.py
pyls/plugins/definition.py
pyls/plugins/flake8_lint.py
pyls/plugins/folding.py
pyls/plugins/highlight.py
pyls/plugins/hover.py
pyls/plugins/jedi_completion.py
pyls/plugins/jedi_rename.py
pyls/plugins/mccabe_lint.py
pyls/plugins/preload_imports.py
pyls/plugins/pycodestyle_lint.py
pyls/plugins/pydocstyle_lint.py
pyls/plugins/pyflakes_lint.py
pyls/plugins/pylint_lint.py
pyls/plugins/references.py
pyls/plugins/rope_completion.py
pyls/plugins/rope_rename.py
pyls/plugins/signature.py
pyls/plugins/symbols.py
pyls/plugins/yapf_format.py
python_language_server-0.36.1.dist-info/LICENSE
python_language_server-0.36.1.dist-info/METADATA
python_language_server-0.36.1.dist-info/WHEEL
python_language_server-0.36.1.dist-info/entry_points.txt
python_language_server-0.36.1.dist-info/top_level.txt
python_language_server-0.36.1.dist-info/RECORD
