Metadata-Version: 2.1
Name: python-language-server
Version: 0.36.1
Summary: Python Language Server for the Language Server Protocol
Home-page: https://github.com/palantir/python-language-server
Author: Palantir Technologies, Inc.
License: UNKNOWN
Platform: UNKNOWN
Provides-Extra: all
Provides-Extra: autopep8
Provides-Extra: flake8
Provides-Extra: mccabe
Provides-Extra: pycodestyle
Provides-Extra: pydocstyle
Provides-Extra: pyflakes
Provides-Extra: pylint
Provides-Extra: rope
Provides-Extra: yapf
Provides-Extra: test
